unit_gen/__init__.py
unit_gen/unittest_case_generator.py
python_unit_generator-0.0.4.dist-info/METADATA
python_unit_generator-0.0.4.dist-info/WHEEL
python_unit_generator-0.0.4.dist-info/RECORD
