Metadata-Version: 2.1
Name: python-unit-generator
Version: 0.0.4
Summary: generate unit tests for python code
Project-URL: Homepage, https://github.com/RomanMIzulin/python_unit_generator
Project-URL: Bug Tracker, https://github.com/RomanMIzulin/python_unit_generator/issues
Author-email: Roman Matveev <dazyra@gmail.com>
Classifier: License :: OSI Approved :: MIT License
Classifier: Programming Language :: Python :: 3
Requires-Python: >=3.10
